{
  "effect_zhucheng_niaofei" : {
    "f1" : {
      "start" : {
        "x" : "-109.1",
        "y" : "171.4",
        "rotation" : "4.28",
        "scaleX" : "-0.55",
        "scaleY" : "0.55",
        "opacity" : "137"
      }
    },
    "order" : "1"
  },
  "effect_zhucheng_yun" : {
    "f1" : {
      "start" : {
        "x" : "0",
        "y" : "0",
        "rotation" : "0",
        "scaleX" : "1",
        "scaleY" : "1",
        "opacity" : "255"
      }
    },
    "order" : "0"
  },
  "events" : {
    "f601" : "finish"
  }
}