{
  "target" : {
    "f1" : {
      "start" : {
        "x" : "0",
        "y" : "0",
        "rotation" : "0",
        "scaleX" : "1",
        "scaleY" : "1.53",
        "opacity" : "0",
        "dx" : "0",
        "dy" : "0"
      }
    },
    "f5" : {
      "start" : {
        "x" : "0",
        "y" : "0",
        "rotation" : "0",
        "scaleX" : "1",
        "scaleY" : "1.53",
        "opacity" : "0",
        "dx" : "0",
        "dy" : "0"
      },
      "nextFrame" : "f10",
      "frames" : "6"
    },
    "f10" : {
      "start" : {
        "x" : "0",
        "y" : "0",
        "rotation" : "0",
        "scaleX" : "1",
        "scaleY" : "1",
        "opacity" : "255",
        "dx" : "0",
        "dy" : "0"
      }
    }
  },
  "events" : {
    "f11" : "finish"
  }
}